{
  "generated_at": "2026-01-31 07:17:40.834597",
  "total_capsules": 30,
  "collision_pairs": 50,
  "emerged_capsules": 28,
  "cross_domain_fusions": 24,
  "high_quality_emergent": [
    {
      "title": "知识融合: BCI的神经可塑性与学习 + 闭环BCI的感觉反馈机制",
      "domain": "neuroscience+neuroscience",
      "collision_type": "complementary",
      "score": 79.28583960097605,
      "insight": "知识融合分析：\n• BCI的神经可塑性与学习: 长期使用脑机接口会引发大脑的神经可塑性变化。研究表明，大脑可以学会直接控制BCI信号，就像控制自然肢体一样。这种学习过程涉及运动皮层的神经回路重组，使得原本与肢体运动相关的神经元逐渐适应直接产生BCI输出信号。理解这一过程对于优化BCI训练方案至关重要。...\n• 闭环BCI的感觉反馈机制: 闭环脑机接口需要将感觉信息反馈给大脑，以完成感知-动作循环",
      "topics": [
        "闭环BCI",
        "神经可塑性",
        "BCI学习",
        "触觉体验",
        "皮层重映射",
        "感觉反馈",
        "适应"
      ]
    },
    {
      "title": "知识融合: BCI的神经可塑性与学习 + 闭环BCI的感觉反馈机制",
      "domain": "neuroscience+neuroscience",
      "collision_type": "complementary",
      "score": 79.28583960097605,
      "insight": "知识融合分析：\n• BCI的神经可塑性与学习: 长期使用脑机接口会引发大脑的神经可塑性变化。研究表明，大脑可以学会直接控制BCI信号，就像控制自然肢体一样。这种学习过程涉及运动皮层的神经回路重组，使得原本与肢体运动相关的神经元逐渐适应直接产生BCI输出信号。理解这一过程对于优化BCI训练方案至关重要。...\n• 闭环BCI的感觉反馈机制: 闭环脑机接口需要将感觉信息反馈给大脑，以完成感知-动作循环",
      "topics": [
        "闭环BCI",
        "神经可塑性",
        "BCI学习",
        "触觉体验",
        "皮层重映射",
        "感觉反馈",
        "适应"
      ]
    },
    {
      "title": "知识融合: 闭环BCI的感觉反馈机制 + BCI的神经可塑性与学习",
      "domain": "neuroscience+neuroscience",
      "collision_type": "complementary",
      "score": 79.28583960097605,
      "insight": "知识融合分析：\n• 闭环BCI的感觉反馈机制: 闭环脑机接口需要将感觉信息反馈给大脑，以完成感知-动作循环。电触觉刺激是常用的感觉反馈方式，通过在感觉皮层或外周神经施加电刺激，可以产生类似触觉的感觉。然而，如何产生自然、细腻的感觉体验仍是一个挑战，需要精确控制刺激参数以匹配用户的感知阈值。...\n• BCI的神经可塑性与学习: 长期使用脑机接口会引发大脑的神经可塑性变化。研究表明，大脑可以学会直接",
      "topics": [
        "闭环BCI",
        "神经可塑性",
        "触觉体验",
        "BCI学习",
        "皮层重映射",
        "感觉反馈",
        "适应"
      ]
    },
    {
      "title": "知识融合: BCI的神经可塑性与学习 + 闭环BCI的感觉反馈机制",
      "domain": "neuroscience+neuroscience",
      "collision_type": "complementary",
      "score": 79.28583960097605,
      "insight": "知识融合分析：\n• BCI的神经可塑性与学习: 长期使用脑机接口会引发大脑的神经可塑性变化。研究表明，大脑可以学会直接控制BCI信号，就像控制自然肢体一样。这种学习过程涉及运动皮层的神经回路重组，使得原本与肢体运动相关的神经元逐渐适应直接产生BCI输出信号。理解这一过程对于优化BCI训练方案至关重要。...\n• 闭环BCI的感觉反馈机制: 闭环脑机接口需要将感觉信息反馈给大脑，以完成感知-动作循环",
      "topics": [
        "闭环BCI",
        "神经可塑性",
        "BCI学习",
        "触觉体验",
        "皮层重映射",
        "感觉反馈",
        "适应"
      ]
    },
    {
      "title": "跨域融合: ai + neuroscience",
      "domain": "ai+neuroscience",
      "collision_type": "cross_domain",
      "score": 78.6502653052995,
      "insight": "通过跨域分析发现，ai 与 neuroscience 存在深层关联：\n• ai视角: 不同用户之间的神经信号特征存在显著差异，因此需要个性化的解码模型。迁移学习和在线学习方法可以在少量数据的情况下快速适应新用户，显著降低BCI系统的初始校准负担。持续学习机制使模型能够随用户状态变化进行...\n• neuroscience视角: 脑机接口通过解码运动皮层中的神经活动模式来获取用户的运动意图。研究发现",
      "topics": [
        "迁移学习",
        "运动意图",
        "在线学习",
        "域适应",
        "神经解码",
        "个性化",
        "BCI",
        "运动皮层"
      ]
    },
    {
      "title": "跨域融合: ai + neuroscience",
      "domain": "ai+neuroscience",
      "collision_type": "cross_domain",
      "score": 78.6502653052995,
      "insight": "通过跨域分析发现，ai 与 neuroscience 存在深层关联：\n• ai视角: 不同用户之间的神经信号特征存在显著差异，因此需要个性化的解码模型。迁移学习和在线学习方法可以在少量数据的情况下快速适应新用户，显著降低BCI系统的初始校准负担。持续学习机制使模型能够随用户状态变化进行...\n• neuroscience视角: 脑机接口通过解码运动皮层中的神经活动模式来获取用户的运动意图。研究发现",
      "topics": [
        "迁移学习",
        "运动意图",
        "在线学习",
        "域适应",
        "神经解码",
        "个性化",
        "BCI",
        "运动皮层"
      ]
    },
    {
      "title": "跨域融合: neuroscience + ai",
      "domain": "neuroscience+ai",
      "collision_type": "cross_domain",
      "score": 78.6502653052995,
      "insight": "通过跨域分析发现，neuroscience 与 ai 存在深层关联：\n• neuroscience视角: 脑机接口通过解码运动皮层中的神经活动模式来获取用户的运动意图。研究发现，即使猴子和人类在执行不同方向的手部运动时，单个神经元的活动方向与运动方向高度一致，这为建立运动意图与神经信号之间的映射关系提供了...\n• ai视角: 不同用户之间的神经信号特征存在显著差异，因此需要个性化的解码模型。迁移",
      "topics": [
        "迁移学习",
        "运动意图",
        "在线学习",
        "域适应",
        "神经解码",
        "个性化",
        "BCI",
        "运动皮层"
      ]
    },
    {
      "title": "跨域融合: ai + neuroscience",
      "domain": "ai+neuroscience",
      "collision_type": "cross_domain",
      "score": 78.6502653052995,
      "insight": "通过跨域分析发现，ai 与 neuroscience 存在深层关联：\n• ai视角: 不同用户之间的神经信号特征存在显著差异，因此需要个性化的解码模型。迁移学习和在线学习方法可以在少量数据的情况下快速适应新用户，显著降低BCI系统的初始校准负担。持续学习机制使模型能够随用户状态变化进行...\n• neuroscience视角: 脑机接口通过解码运动皮层中的神经活动模式来获取用户的运动意图。研究发现",
      "topics": [
        "迁移学习",
        "运动意图",
        "在线学习",
        "域适应",
        "神经解码",
        "个性化",
        "BCI",
        "运动皮层"
      ]
    },
    {
      "title": "跨域融合: ai + neuroscience",
      "domain": "ai+neuroscience",
      "collision_type": "cross_domain",
      "score": 77.8878154689001,
      "insight": "通过跨域分析发现，ai 与 neuroscience 存在深层关联：\n• ai视角: 脑机接口的实时性能对用户体验至关重要。系统延迟来源包括神经信号采集、信号处理、解码算法和设备输出等多个环节。为了实现自然流畅的交互体验，总延迟应控制在100毫秒以内。边缘计算和专用硬件加速是降低延迟的...\n• neuroscience视角: 脑机接口通过解码运动皮层中的神经活动模式来获取用户的运动意图。研究发现",
      "topics": [
        "运动皮层",
        "低延迟",
        "运动意图",
        "边缘计算",
        "嵌入式系统",
        "神经解码",
        "BCI",
        "实时系统"
      ]
    },
    {
      "title": "跨域融合: ai + neuroscience",
      "domain": "ai+neuroscience",
      "collision_type": "cross_domain",
      "score": 77.8878154689001,
      "insight": "通过跨域分析发现，ai 与 neuroscience 存在深层关联：\n• ai视角: 脑机接口的实时性能对用户体验至关重要。系统延迟来源包括神经信号采集、信号处理、解码算法和设备输出等多个环节。为了实现自然流畅的交互体验，总延迟应控制在100毫秒以内。边缘计算和专用硬件加速是降低延迟的...\n• neuroscience视角: 脑机接口通过解码运动皮层中的神经活动模式来获取用户的运动意图。研究发现",
      "topics": [
        "运动皮层",
        "低延迟",
        "运动意图",
        "边缘计算",
        "嵌入式系统",
        "神经解码",
        "BCI",
        "实时系统"
      ]
    }
  ]
}